MANIFEST.in
setup.py
./__init__.py
./__openerp__.py
./account.py
./l10n_multilang.py
i18n/ar.po
i18n/da.po
i18n/de.po
i18n/es.po
i18n/es_CR.po
i18n/fr.po
i18n/hr.po
i18n/hu.po
i18n/l10n_multilang.pot
i18n/mn.po
i18n/nl.po
i18n/pl.po
i18n/pt.po
i18n/pt_BR.po
i18n/ro.po
i18n/sl.po
i18n/tr.po
i18n/zh_CN.po
openerp_l10n_multilang.egg-info/PKG-INFO
openerp_l10n_multilang.egg-info/SOURCES.txt
openerp_l10n_multilang.egg-info/dependency_links.txt
openerp_l10n_multilang.egg-info/requires.txt
openerp_l10n_multilang.egg-info/top_level.txt